AUTHORS.rst
LICENSE
README.rst
setup.cfg
setup.py
spcrawler/__init__.py
spcrawler/__main__.py
spcrawler/core.py
spcrawler.egg-info/PKG-INFO
spcrawler.egg-info/SOURCES.txt
spcrawler.egg-info/dependency_links.txt
spcrawler.egg-info/entry_points.txt
spcrawler.egg-info/not-zip-safe
spcrawler.egg-info/requires.txt
spcrawler.egg-info/top_level.txt
spcrawler/cmds/__init__.py
spcrawler/cmds/extractor.py
spcrawler/spapi/__init__.py
spcrawler/spapi/crawler.py