Metadata-Version: 2.1
Name: spcrawler
Version: 1.0.1
Summary: spcrawler:  A command-line tool to backup Sharepoint public installations data from open API endpoint
Home-page: https://github.com/ruarxive/spcrawler/
Download-URL: https://github.com/ruarxive/spcrawler/
Author: Ivan Begtin
Author-email: ivan@begtin.tech
License: Apache 2.0
Keywords: backup archive metadata sharepoint
Platform: UNKNOWN
Classifier: Development Status :: 5 - Production/Stable
Classifier: Programming Language :: Python
Classifier: Programming Language :: Python :: 3 :: Only
Classifier: Programming Language :: Python :: 3.6
Classifier: Programming Language :: Python :: 3.7
Classifier: Environment :: Console
Classifier: Intended Audience :: Developers
Classifier: Intended Audience :: System Administrators
Classifier: License :: OSI Approved :: BSD License
Classifier: Topic :: Software Development
Classifier: Topic :: System :: Networking
Classifier: Topic :: Terminals
Classifier: Topic :: Text Processing
Classifier: Topic :: Utilities
Provides-Extra: python_version == "3.0" or python_version == "3.1"
License-File: LICENSE
License-File: AUTHORS.rst
